{
    "richards.Scheduler.schedule": {
        "27 (Vtune Block 287)": 3,
        "22 (Vtune Block 275)": 6,
        "21 (Vtune Block 248)": 5,
        "26 (Vtune Block 249)": 15,
        "Backend Blocks": {
            "30004 (Vtune Block 255)": 9,
            "33005 (Vtune Block 268)": 9,
            "30005 (Vtune Block 261)": 2,
            "33004 (Vtune Block 264)": 9,
            "30001 (Vtune Block 251)": 5,
            "35004 (Vtune Block 280)": 10,
            "33003 (Vtune Block 263)": 34,
            "35001 (Vtune Block 276)": 1,
            "33006 (Vtune Block 274)": 2
        },
        "19 (Vtune Block 246)": 5,
        "31 (Vtune Block 262)": 4,
        "28 (Vtune Block 250)": 1,
        "32 (Vtune Block 289)": 4,
        "29 (Vtune Block 288)": 6,
        "20 (Vtune Block 247)": 1
    },
    "richards.Scheduler$WorkerProcessFunction.apply": {
        "3 (Vtune Block 5)": 10,
        "32 (Vtune Block 30)": 7,
        "9 (Vtune Block 8)": 17,
        "0 (Vtune Block 3)": 1,
        "12 (Vtune Block 10)": 9,
        "14 (Vtune Block 50)": 32,
        "18 (Vtune Block 12)": 12,
        "21 (Vtune Block 13)": 5,
        "Backend Blocks": {
            "24005 (Vtune Block 18)": 12,
            "25005 (Vtune Block 23)": 6,
            "24003 (Vtune Block 14)": 17,
            "7001 (Vtune Block 7)": 5,
            "25006 (Vtune Block 29)": 11,
            "25003 (Vtune Block 19)": 7
        },
        "26 (Vtune Block 48)": 6,
        "20 (Vtune Block 53)": 55,
        "65535 (Vtune Block 2)": 18,
        "8 (Vtune Block 32)": 17,
        "5 (Vtune Block 6)": 1,
        "15 (Vtune Block 11)": 8,
        "2 (Vtune Block 4)": 7
    },
    "richards.Scheduler$IdleProcessFunction.apply": {
        "3 (Vtune Block 5)": 7,
        "15 (Vtune Block 13)": 0,
        "Backend Blocks": {
            "18001 (Vtune Block 14)": 42,
            "12001 (Vtune Block 10)": 46,
            "7001 (Vtune Block 7)": 12
        },
        "9 (Vtune Block 8)": 11,
        "10 (Vtune Block 9)": 0,
        "13 (Vtune Block 11)": 6,
        "65535 (Vtune Block 2)": 10,
        "19 (Vtune Block 15)": 6,
        "2 (Vtune Block 4)": 6
    },
    "richards.Scheduler$DeviceProcessFunction.apply": {
        "3 (Vtune Block 5)": 6,
        "9 (Vtune Block 44)": 9,
        "Backend Blocks": {
            "21005 (Vtune Block 42)": 12,
            "8001 (Vtune Block 8)": 4,
            "21002 (Vtune Block 36)": 10,
            "11007 (Vtune Block 14)": 26,
            "11009 (Vtune Block 18)": 3,
            "11001 (Vtune Block 10)": 7,
            "12003 (Vtune Block 19)": 6,
            "21001 (Vtune Block 32)": 10,
            "12005 (Vtune Block 23)": 13,
            "12006 (Vtune Block 29)": 8
        },
        "10 (Vtune Block 9)": 6,
        "65535 (Vtune Block 2)": 6,
        "19 (Vtune Block 30)": 5,
        "0 (Vtune Block 3)": 1,
        "7 (Vtune Block 7)": 4,
        "2 (Vtune Block 4)": 3
    },
    "richards.Scheduler$HandlerProcessFunction.apply": {
        "3 (Vtune Block 5)": 6,
        "29 (Vtune Block 21)": 8,
        "18 (Vtune Block 74)": 8,
        "25 (Vtune Block 89)": 26,
        "42 (Vtune Block 91)": 104,
        "27 (Vtune Block 20)": 4,
        "11 (Vtune Block 148)": 5,
        "7 (Vtune Block 7)": 9,
        "51 (Vtune Block 119)": 8,
        "Backend Blocks": {
            "44004 (Vtune Block 117)": 9,
            "31011 (Vtune Block 37)": 4,
            "15001 (Vtune Block 128)": 11,
            "22003 (Vtune Block 58)": 14,
            "15003 (Vtune Block 132)": 13,
            "32001 (Vtune Block 38)": 6,
            "26003 (Vtune Block 19)": 14,
            "24001 (Vtune Block 18)": 12,
            "44001 (Vtune Block 107)": 6,
            "38003 (Vtune Block 82)": 6,
            "31001 (Vtune Block 23)": 6,
            "35002 (Vtune Block 75)": 10,
            "22001 (Vtune Block 54)": 9,
            "16001 (Vtune Block 138)": 14,
            "31009 (Vtune Block 33)": 20,
            "12002 (Vtune Block 122)": 8,
            "38001 (Vtune Block 78)": 8,
            "19002 (Vtune Block 14)": 6,
            "31004 (Vtune Block 27)": 11,
            "9002 (Vtune Block 12)": 11,
            "43008 (Vtune Block 106)": 14,
            "43004 (Vtune Block 96)": 22,
            "44003 (Vtune Block 111)": 14,
            "38004 (Vtune Block 88)": 5,
            "43006 (Vtune Block 102)": 28,
            "32003 (Vtune Block 42)": 9
        },
        "36 (Vtune Block 77)": 9,
        "39 (Vtune Block 50)": 4,
        "65535 (Vtune Block 2)": 10,
        "13 (Vtune Block 124)": 24,
        "28 (Vtune Block 52)": 20,
        "30 (Vtune Block 22)": 6,
        "2 (Vtune Block 4)": 7
    }
}